<CAModel>
	<info>
		<model>Segregation</model>
		<rows>8</rows>
		<cols>8</cols>
	</info>	
	<parameters>
		<threshold>0.30</threshold>
	</parameters>
	<cell>
		<r>3</r>
		<c>6</c>
		<state>1</state>
	</cell>
	<cell>
		<r>1</r>
		<c>1</c>
		<state>2</state>
	</cell>
	<cell>
		<r>0</r>
		<c>4</c>
		<state>1</state>
	</cell>	
	<cell>
		<r>7</r>
		<c>7</c>
		<state>1</state>
	</cell>	
		<cell>
		<r>2</r>
		<c>2</c>
		<state>2</state>
	</cell>	
		<cell>
		<r>5</r>
		<c>5</c>
		<state>1</state>
	</cell>	
		<cell>
		<r>4</r>
		<c>1</c>
		<state>1</state>
	</cell>	
		<cell>
		<r>1</r>
		<c>0</c>
		<state>1</state>
	</cell>	
		<cell>
		<r>0</r>
		<c>7</c>
		<state>2</state>
	</cell>	
		<cell>
		<r>6</r>
		<c>3</c>
		<state>2</state>
	</cell>	
</CAModel>
